{
    "accuracy": 100,
    "contest_combos": null,
    "contest_effect": null,
    "contest_type": {
        "name": "cute",
        "url": "/pokedex/contest-type/3/"
    },
    "damage_class": {
        "name": "physical",
        "url": "/pokedex/move-damage-class/2/"
    },
    "effect_chance": null,
    "effect_changes": [],
    "effect_entries": [
        {
            "effect": "Inflicts regular damage, then the user immediately switches out, and the trainer selects a replacement Pok\u00e9mon from the party.  If the target faints from this attack, the user's trainer selects the new Pok\u00e9mon to send out first.  If the user is the last Pok\u00e9mon in its party that can battle, it will not switch out.\n\nThe user may be hit by pursuit when it switches out, if it has been targeted and pursuit has not yet been used.\n\nThis move may be used even if the user is under the effect of ingrain.  ingrain's effect will end.",
            "language": {
                "name": "en",
                "url": "/pokedex/language/9/"
            },
            "short_effect": "User must switch out after attacking."
        }
    ],
    "flavor_text_entries": [
        {
            "flavor_text": "After making its\nattack, the user\nrushes back to switch\nplaces with a party\nPok\u00e9mon in waiting.",
            "language": {
                "name": "en",
                "url": "/pokedex/language/9/"
            },
            "version_group": {
                "name": "diamond-pearl",
                "url": "/pokedex/version-group/8/"
            }
        },
        {
            "flavor_text": "After making its\nattack, the user\nrushes back to switch\nplaces with a party\nPok\u00e9mon in waiting.",
            "language": {
                "name": "en",
                "url": "/pokedex/language/9/"
            },
            "version_group": {
                "name": "platinum",
                "url": "/pokedex/version-group/9/"
            }
        },
        {
            "flavor_text": "After making its\nattack, the user\nrushes back to switch\nplaces with a party\nPok\u00e9mon in waiting.",
            "language": {
                "name": "en",
                "url": "/pokedex/language/9/"
            },
            "version_group": {
                "name": "heartgold-soulsilver",
                "url": "/pokedex/version-group/10/"
            }
        },
        {
            "flavor_text": "Apr\u00e8s son attaque, le lanceur revient \u00e0\ntoute vitesse et change de place avec\nun Pok\u00e9mon de l\u2019\u00e9quipe pr\u00eat au combat.",
            "language": {
                "name": "fr",
                "url": "/pokedex/language/5/"
            },
            "version_group": {
                "name": "black-white",
                "url": "/pokedex/version-group/11/"
            }
        },
        {
            "flavor_text": "After making its attack, the user\nrushes back to switch places with\na party Pok\u00e9mon in waiting.",
            "language": {
                "name": "en",
                "url": "/pokedex/language/9/"
            },
            "version_group": {
                "name": "black-white",
                "url": "/pokedex/version-group/11/"
            }
        },
        {
            "flavor_text": "After making its attack, the user\nrushes back to switch places with\na party Pok\u00e9mon in waiting.",
            "language": {
                "name": "en",
                "url": "/pokedex/language/9/"
            },
            "version_group": {
                "name": "black-2-white-2",
                "url": "/pokedex/version-group/14/"
            }
        },
        {
            "flavor_text": "\u3053\u3046\u3052\u304d\u3000\u3057\u305f\u3042\u3068\n\u3082\u306e\u3059\u3054\u3044\u3000\u30b9\u30d4\u30fc\u30c9\u3067\u3000\u3082\u3069\u3063\u3066\u304d\u3066\n\u3072\u304b\u3048\u3000\u30dd\u30b1\u30e2\u30f3\u3068\u3000\u3044\u308c\u304b\u308f\u308b\u3002",
            "language": {
                "name": "ja-Hrkt",
                "url": "/pokedex/language/1/"
            },
            "version_group": {
                "name": "x-y",
                "url": "/pokedex/version-group/15/"
            }
        },
        {
            "flavor_text": "\uacf5\uaca9\ud55c \ub4a4\n\uad49\uc7a5\ud55c \uc2a4\ud53c\ub4dc\ub85c \ub3cc\uc544\uc640\uc11c\n\uad50\ub300 \ud3ec\ucf13\ubaac\uacfc \uad50\uccb4\ud55c\ub2e4.",
            "language": {
                "name": "ko",
                "url": "/pokedex/language/3/"
            },
            "version_group": {
                "name": "x-y",
                "url": "/pokedex/version-group/15/"
            }
        },
        {
            "flavor_text": "Apr\u00e8s son attaque, le lanceur revient \u00e0 toute\nvitesse et change de place avec un Pok\u00e9mon\nde l\u2019\u00e9quipe pr\u00eat au combat.",
            "language": {
                "name": "fr",
                "url": "/pokedex/language/5/"
            },
            "version_group": {
                "name": "x-y",
                "url": "/pokedex/version-group/15/"
            }
        },
        {
            "flavor_text": "Nach der Attacke eilt der Anwender zur\u00fcck und\ntauscht den Platz mit einem anderen Pok\u00e9mon.",
            "language": {
                "name": "de",
                "url": "/pokedex/language/6/"
            },
            "version_group": {
                "name": "x-y",
                "url": "/pokedex/version-group/15/"
            }
        },
        {
            "flavor_text": "Tras atacar, vuelve a toda prisa para dar paso a\notro Pok\u00e9mon del equipo.",
            "language": {
                "name": "es",
                "url": "/pokedex/language/7/"
            },
            "version_group": {
                "name": "x-y",
                "url": "/pokedex/version-group/15/"
            }
        },
        {
            "flavor_text": "Chi usa questa mossa fa marcia indietro per farsi\nsostituire dopo aver sferrato l\u2019attacco.",
            "language": {
                "name": "it",
                "url": "/pokedex/language/8/"
            },
            "version_group": {
                "name": "x-y",
                "url": "/pokedex/version-group/15/"
            }
        },
        {
            "flavor_text": "After making its attack, the user\nrushes back to switch places with\na party Pok\u00e9mon in waiting.",
            "language": {
                "name": "en",
                "url": "/pokedex/language/9/"
            },
            "version_group": {
                "name": "x-y",
                "url": "/pokedex/version-group/15/"
            }
        },
        {
            "flavor_text": "\u653b\u6483\u3057\u305f\u3042\u3068\n\u3082\u306e\u3059\u3054\u3044\u3000\u30b9\u30d4\u30fc\u30c9\u3067\u3000\u3082\u3069\u3063\u3066\u304d\u3066\n\u63a7\u3048\u306e\u3000\u30dd\u30b1\u30e2\u30f3\u3068\u3000\u5165\u308c\u66ff\u308f\u308b\u3002",
            "language": {
                "name": "ja",
                "url": "/pokedex/language/11/"
            },
            "version_group": {
                "name": "x-y",
                "url": "/pokedex/version-group/15/"
            }
        },
        {
            "flavor_text": "\u3053\u3046\u3052\u304d\u3000\u3057\u305f\u3042\u3068\n\u3082\u306e\u3059\u3054\u3044\u3000\u30b9\u30d4\u30fc\u30c9\u3067\u3000\u3082\u3069\u3063\u3066\u304d\u3066\n\u3072\u304b\u3048\u3000\u30dd\u30b1\u30e2\u30f3\u3068\u3000\u3044\u308c\u304b\u308f\u308b\u3002",
            "language": {
                "name": "ja-Hrkt",
                "url": "/pokedex/language/1/"
            },
            "version_group": {
                "name": "omega-ruby-alpha-sapphire",
                "url": "/pokedex/version-group/16/"
            }
        },
        {
            "flavor_text": "\uacf5\uaca9\ud55c \ub4a4\n\uad49\uc7a5\ud55c \uc2a4\ud53c\ub4dc\ub85c \ub3cc\uc544\uc640\uc11c\n\uad50\ub300 \ud3ec\ucf13\ubaac\uacfc \uad50\uccb4\ud55c\ub2e4.",
            "language": {
                "name": "ko",
                "url": "/pokedex/language/3/"
            },
            "version_group": {
                "name": "omega-ruby-alpha-sapphire",
                "url": "/pokedex/version-group/16/"
            }
        },
        {
            "flavor_text": "Apr\u00e8s son attaque, le lanceur revient \u00e0 toute\nvitesse et change de place avec un Pok\u00e9mon\nde l\u2019\u00e9quipe pr\u00eat au combat.",
            "language": {
                "name": "fr",
                "url": "/pokedex/language/5/"
            },
            "version_group": {
                "name": "omega-ruby-alpha-sapphire",
                "url": "/pokedex/version-group/16/"
            }
        },
        {
            "flavor_text": "Nach der Attacke eilt der Anwender zur\u00fcck und\ntauscht den Platz mit einem anderen Pok\u00e9mon.",
            "language": {
                "name": "de",
                "url": "/pokedex/language/6/"
            },
            "version_group": {
                "name": "omega-ruby-alpha-sapphire",
                "url": "/pokedex/version-group/16/"
            }
        },
        {
            "flavor_text": "Tras atacar, vuelve a toda prisa para dar paso a \notro Pok\u00e9mon del equipo.",
            "language": {
                "name": "es",
                "url": "/pokedex/language/7/"
            },
            "version_group": {
                "name": "omega-ruby-alpha-sapphire",
                "url": "/pokedex/version-group/16/"
            }
        },
        {
            "flavor_text": "Chi usa questa mossa fa marcia indietro per farsi\nsostituire dopo aver sferrato l\u2019attacco.",
            "language": {
                "name": "it",
                "url": "/pokedex/language/8/"
            },
            "version_group": {
                "name": "omega-ruby-alpha-sapphire",
                "url": "/pokedex/version-group/16/"
            }
        },
        {
            "flavor_text": "After making its attack, the user\nrushes back to switch places with\na party Pok\u00e9mon in waiting.",
            "language": {
                "name": "en",
                "url": "/pokedex/language/9/"
            },
            "version_group": {
                "name": "omega-ruby-alpha-sapphire",
                "url": "/pokedex/version-group/16/"
            }
        },
        {
            "flavor_text": "\u653b\u6483\u3057\u305f\u3042\u3068\n\u3082\u306e\u3059\u3054\u3044\u3000\u30b9\u30d4\u30fc\u30c9\u3067\u3000\u3082\u3069\u3063\u3066\u304d\u3066\n\u63a7\u3048\u306e\u3000\u30dd\u30b1\u30e2\u30f3\u3068\u3000\u5165\u308c\u66ff\u308f\u308b\u3002",
            "language": {
                "name": "ja",
                "url": "/pokedex/language/11/"
            },
            "version_group": {
                "name": "omega-ruby-alpha-sapphire",
                "url": "/pokedex/version-group/16/"
            }
        },
        {
            "flavor_text": "\u3053\u3046\u3052\u304d\u3000\u3057\u305f\u3042\u3068\n\u3082\u306e\u3059\u3054\u3044\u3000\u30b9\u30d4\u30fc\u30c9\u3067\u3000\u3082\u3069\u3063\u3066\u304d\u3066\n\u3072\u304b\u3048\u3000\u30dd\u30b1\u30e2\u30f3\u3068\u3000\u3044\u308c\u304b\u308f\u308b\u3002",
            "language": {
                "name": "ja-Hrkt",
                "url": "/pokedex/language/1/"
            },
            "version_group": {
                "name": "sun-moon",
                "url": "/pokedex/version-group/17/"
            }
        },
        {
            "flavor_text": "\uacf5\uaca9\ud55c \ub4a4\n\uad49\uc7a5\ud55c \uc2a4\ud53c\ub4dc\ub85c \ub3cc\uc544\uc640\uc11c\n\uad50\ub300 \ud3ec\ucf13\ubaac\uacfc \uad50\uccb4\ud55c\ub2e4.",
            "language": {
                "name": "ko",
                "url": "/pokedex/language/3/"
            },
            "version_group": {
                "name": "sun-moon",
                "url": "/pokedex/version-group/17/"
            }
        },
        {
            "flavor_text": "\u653b\u64ca\u5f8c\u8fc5\u901f\u8fd4\u56de\uff0c\n\u548c\u5f8c\u5099\u5bf6\u53ef\u5922\u9032\u884c\u66ff\u63db\u3002",
            "language": {
                "name": "zh-Hant",
                "url": "/pokedex/language/4/"
            },
            "version_group": {
                "name": "sun-moon",
                "url": "/pokedex/version-group/17/"
            }
        },
        {
            "flavor_text": "Apr\u00e8s son attaque, le lanceur revient \u00e0 toute\nvitesse et change de place avec un Pok\u00e9mon\nde l\u2019\u00e9quipe pr\u00eat au combat.",
            "language": {
                "name": "fr",
                "url": "/pokedex/language/5/"
            },
            "version_group": {
                "name": "sun-moon",
                "url": "/pokedex/version-group/17/"
            }
        },
        {
            "flavor_text": "Nach der Attacke eilt der Anwender zur\u00fcck und\ntauscht den Platz mit einem anderen Pok\u00e9mon.",
            "language": {
                "name": "de",
                "url": "/pokedex/language/6/"
            },
            "version_group": {
                "name": "sun-moon",
                "url": "/pokedex/version-group/17/"
            }
        },
        {
            "flavor_text": "Tras atacar, vuelve a toda prisa para dar paso a \notro Pok\u00e9mon del equipo.",
            "language": {
                "name": "es",
                "url": "/pokedex/language/7/"
            },
            "version_group": {
                "name": "sun-moon",
                "url": "/pokedex/version-group/17/"
            }
        },
        {
            "flavor_text": "Chi usa questa mossa fa marcia indietro per farsi\nsostituire dopo aver sferrato l\u2019attacco.",
            "language": {
                "name": "it",
                "url": "/pokedex/language/8/"
            },
            "version_group": {
                "name": "sun-moon",
                "url": "/pokedex/version-group/17/"
            }
        },
        {
            "flavor_text": "After making its attack, the user rushes back to\nswitch places with a party Pok\u00e9mon in waiting.",
            "language": {
                "name": "en",
                "url": "/pokedex/language/9/"
            },
            "version_group": {
                "name": "sun-moon",
                "url": "/pokedex/version-group/17/"
            }
        },
        {
            "flavor_text": "\u653b\u6483\u3057\u305f\u3042\u3068\n\u3082\u306e\u3059\u3054\u3044\u3000\u30b9\u30d4\u30fc\u30c9\u3067\u3000\u3082\u3069\u3063\u3066\u304d\u3066\n\u63a7\u3048\u306e\u3000\u30dd\u30b1\u30e2\u30f3\u3068\u3000\u5165\u308c\u66ff\u308f\u308b\u3002",
            "language": {
                "name": "ja",
                "url": "/pokedex/language/11/"
            },
            "version_group": {
                "name": "sun-moon",
                "url": "/pokedex/version-group/17/"
            }
        },
        {
            "flavor_text": "\u5728\u653b\u51fb\u4e4b\u540e\u6025\u901f\u8fd4\u56de\uff0c\n\u548c\u540e\u5907\u5b9d\u53ef\u68a6\u8fdb\u884c\u66ff\u6362\u3002",
            "language": {
                "name": "zh-Hans",
                "url": "/pokedex/language/12/"
            },
            "version_group": {
                "name": "sun-moon",
                "url": "/pokedex/version-group/17/"
            }
        },
        {
            "flavor_text": "\u3053\u3046\u3052\u304d\u3000\u3057\u305f\u3042\u3068\n\u3082\u306e\u3059\u3054\u3044\u3000\u30b9\u30d4\u30fc\u30c9\u3067\u3000\u3082\u3069\u3063\u3066\u304d\u3066\n\u3072\u304b\u3048\u3000\u30dd\u30b1\u30e2\u30f3\u3068\u3000\u3044\u308c\u304b\u308f\u308b\u3002",
            "language": {
                "name": "ja-Hrkt",
                "url": "/pokedex/language/1/"
            },
            "version_group": {
                "name": "ultra-sun-ultra-moon",
                "url": "/pokedex/version-group/18/"
            }
        },
        {
            "flavor_text": "\uacf5\uaca9\ud55c \ub4a4\n\uad49\uc7a5\ud55c \uc2a4\ud53c\ub4dc\ub85c \ub3cc\uc544\uc640\uc11c\n\uad50\ub300 \ud3ec\ucf13\ubaac\uacfc \uad50\uccb4\ud55c\ub2e4.",
            "language": {
                "name": "ko",
                "url": "/pokedex/language/3/"
            },
            "version_group": {
                "name": "ultra-sun-ultra-moon",
                "url": "/pokedex/version-group/18/"
            }
        },
        {
            "flavor_text": "\u653b\u64ca\u5f8c\u8fc5\u901f\u8fd4\u56de\uff0c\n\u548c\u5f8c\u5099\u5bf6\u53ef\u5922\u9032\u884c\u66ff\u63db\u3002",
            "language": {
                "name": "zh-Hant",
                "url": "/pokedex/language/4/"
            },
            "version_group": {
                "name": "ultra-sun-ultra-moon",
                "url": "/pokedex/version-group/18/"
            }
        },
        {
            "flavor_text": "Apr\u00e8s son attaque, le lanceur revient \u00e0 toute\nvitesse et change de place avec un Pok\u00e9mon\nde l\u2019\u00e9quipe pr\u00eat au combat.",
            "language": {
                "name": "fr",
                "url": "/pokedex/language/5/"
            },
            "version_group": {
                "name": "ultra-sun-ultra-moon",
                "url": "/pokedex/version-group/18/"
            }
        },
        {
            "flavor_text": "Nach der Attacke eilt der Anwender zur\u00fcck und\ntauscht den Platz mit einem anderen Pok\u00e9mon.",
            "language": {
                "name": "de",
                "url": "/pokedex/language/6/"
            },
            "version_group": {
                "name": "ultra-sun-ultra-moon",
                "url": "/pokedex/version-group/18/"
            }
        },
        {
            "flavor_text": "Tras atacar, vuelve a toda prisa para dar paso a \notro Pok\u00e9mon del equipo.",
            "language": {
                "name": "es",
                "url": "/pokedex/language/7/"
            },
            "version_group": {
                "name": "ultra-sun-ultra-moon",
                "url": "/pokedex/version-group/18/"
            }
        },
        {
            "flavor_text": "Chi usa questa mossa fa marcia indietro per farsi\nsostituire dopo aver sferrato l\u2019attacco.",
            "language": {
                "name": "it",
                "url": "/pokedex/language/8/"
            },
            "version_group": {
                "name": "ultra-sun-ultra-moon",
                "url": "/pokedex/version-group/18/"
            }
        },
        {
            "flavor_text": "After making its attack, the user rushes back to\nswitch places with a party Pok\u00e9mon in waiting.",
            "language": {
                "name": "en",
                "url": "/pokedex/language/9/"
            },
            "version_group": {
                "name": "ultra-sun-ultra-moon",
                "url": "/pokedex/version-group/18/"
            }
        },
        {
            "flavor_text": "\u653b\u6483\u3057\u305f\u3042\u3068\n\u3082\u306e\u3059\u3054\u3044\u3000\u30b9\u30d4\u30fc\u30c9\u3067\u3000\u3082\u3069\u3063\u3066\u304d\u3066\n\u63a7\u3048\u306e\u3000\u30dd\u30b1\u30e2\u30f3\u3068\u3000\u5165\u308c\u66ff\u308f\u308b\u3002",
            "language": {
                "name": "ja",
                "url": "/pokedex/language/11/"
            },
            "version_group": {
                "name": "ultra-sun-ultra-moon",
                "url": "/pokedex/version-group/18/"
            }
        },
        {
            "flavor_text": "\u5728\u653b\u51fb\u4e4b\u540e\u6025\u901f\u8fd4\u56de\uff0c\n\u548c\u540e\u5907\u5b9d\u53ef\u68a6\u8fdb\u884c\u66ff\u6362\u3002",
            "language": {
                "name": "zh-Hans",
                "url": "/pokedex/language/12/"
            },
            "version_group": {
                "name": "ultra-sun-ultra-moon",
                "url": "/pokedex/version-group/18/"
            }
        },
        {
            "flavor_text": "\u3053\u3046\u3052\u304d\u3000\u3057\u305f\u3042\u3068\n\u3082\u306e\u3059\u3054\u3044\u3000\u30b9\u30d4\u30fc\u30c9\u3067\u3000\u3082\u3069\u3063\u3066\u304d\u3066\n\u3072\u304b\u3048\u3000\u30dd\u30b1\u30e2\u30f3\u3068\u3000\u3044\u308c\u304b\u308f\u308b\u3002",
            "language": {
                "name": "ja-Hrkt",
                "url": "/pokedex/language/1/"
            },
            "version_group": {
                "name": "lets-go-pikachu-lets-go-eevee",
                "url": "/pokedex/version-group/19/"
            }
        },
        {
            "flavor_text": "\uacf5\uaca9\ud55c \ub4a4\n\uad49\uc7a5\ud55c \uc2a4\ud53c\ub4dc\ub85c \ub3cc\uc544\uc640\uc11c\n\uad50\ub300 \ud3ec\ucf13\ubaac\uacfc \uad50\uccb4\ud55c\ub2e4.",
            "language": {
                "name": "ko",
                "url": "/pokedex/language/3/"
            },
            "version_group": {
                "name": "lets-go-pikachu-lets-go-eevee",
                "url": "/pokedex/version-group/19/"
            }
        },
        {
            "flavor_text": "\u653b\u64ca\u5f8c\u8fc5\u901f\u8fd4\u56de\uff0c\n\u548c\u5f8c\u5099\u5bf6\u53ef\u5922\u9032\u884c\u66ff\u63db\u3002",
            "language": {
                "name": "zh-Hant",
                "url": "/pokedex/language/4/"
            },
            "version_group": {
                "name": "lets-go-pikachu-lets-go-eevee",
                "url": "/pokedex/version-group/19/"
            }
        },
        {
            "flavor_text": "Apr\u00e8s son attaque, le lanceur revient \u00e0 toute vitesse\net change de place avec un Pok\u00e9mon de l\u2019\u00e9quipe\npr\u00eat au combat.",
            "language": {
                "name": "fr",
                "url": "/pokedex/language/5/"
            },
            "version_group": {
                "name": "lets-go-pikachu-lets-go-eevee",
                "url": "/pokedex/version-group/19/"
            }
        },
        {
            "flavor_text": "Nach der Attacke eilt der Anwender zur\u00fcck und\ntauscht den Platz mit einem anderen Pok\u00e9mon.",
            "language": {
                "name": "de",
                "url": "/pokedex/language/6/"
            },
            "version_group": {
                "name": "lets-go-pikachu-lets-go-eevee",
                "url": "/pokedex/version-group/19/"
            }
        },
        {
            "flavor_text": "Tras atacar, vuelve a toda prisa para dar paso a \notro Pok\u00e9mon del equipo.",
            "language": {
                "name": "es",
                "url": "/pokedex/language/7/"
            },
            "version_group": {
                "name": "lets-go-pikachu-lets-go-eevee",
                "url": "/pokedex/version-group/19/"
            }
        },
        {
            "flavor_text": "Chi usa questa mossa fa marcia indietro per farsi\nsostituire dopo aver sferrato l\u2019attacco.",
            "language": {
                "name": "it",
                "url": "/pokedex/language/8/"
            },
            "version_group": {
                "name": "lets-go-pikachu-lets-go-eevee",
                "url": "/pokedex/version-group/19/"
            }
        },
        {
            "flavor_text": "After making its attack, the user rushes back to\nswitch places with a party Pok\u00e9mon in waiting.",
            "language": {
                "name": "en",
                "url": "/pokedex/language/9/"
            },
            "version_group": {
                "name": "lets-go-pikachu-lets-go-eevee",
                "url": "/pokedex/version-group/19/"
            }
        },
        {
            "flavor_text": "\u653b\u6483\u3057\u305f\u3042\u3068\n\u3082\u306e\u3059\u3054\u3044\u3000\u30b9\u30d4\u30fc\u30c9\u3067\u3000\u3082\u3069\u3063\u3066\u304d\u3066\n\u63a7\u3048\u306e\u3000\u30dd\u30b1\u30e2\u30f3\u3068\u3000\u5165\u308c\u66ff\u308f\u308b\u3002",
            "language": {
                "name": "ja",
                "url": "/pokedex/language/11/"
            },
            "version_group": {
                "name": "lets-go-pikachu-lets-go-eevee",
                "url": "/pokedex/version-group/19/"
            }
        },
        {
            "flavor_text": "\u5728\u653b\u51fb\u4e4b\u540e\u6025\u901f\u8fd4\u56de\uff0c\n\u548c\u540e\u5907\u5b9d\u53ef\u68a6\u8fdb\u884c\u66ff\u6362\u3002",
            "language": {
                "name": "zh-Hans",
                "url": "/pokedex/language/12/"
            },
            "version_group": {
                "name": "lets-go-pikachu-lets-go-eevee",
                "url": "/pokedex/version-group/19/"
            }
        },
        {
            "flavor_text": "\u3053\u3046\u3052\u304d\u3000\u3057\u305f\u3042\u3068\n\u3082\u306e\u3059\u3054\u3044\u3000\u30b9\u30d4\u30fc\u30c9\u3067\u3000\u3082\u3069\u3063\u3066\u304d\u3066\n\u3072\u304b\u3048\u3000\u30dd\u30b1\u30e2\u30f3\u3068\u3000\u3044\u308c\u304b\u308f\u308b\u3002",
            "language": {
                "name": "ja-Hrkt",
                "url": "/pokedex/language/1/"
            },
            "version_group": {
                "name": "sword-shield",
                "url": "/pokedex/version-group/20/"
            }
        },
        {
            "flavor_text": "\uacf5\uaca9\ud55c \ub4a4\n\uad49\uc7a5\ud55c \uc2a4\ud53c\ub4dc\ub85c \ub3cc\uc544\uc640\uc11c\n\uad50\ub300 \ud3ec\ucf13\ubaac\uacfc \uad50\uccb4\ud55c\ub2e4.",
            "language": {
                "name": "ko",
                "url": "/pokedex/language/3/"
            },
            "version_group": {
                "name": "sword-shield",
                "url": "/pokedex/version-group/20/"
            }
        },
        {
            "flavor_text": "\u653b\u64ca\u5f8c\u8fc5\u901f\u8fd4\u56de\uff0c\n\u548c\u5f8c\u5099\u5bf6\u53ef\u5922\u9032\u884c\u66ff\u63db\u3002",
            "language": {
                "name": "zh-Hant",
                "url": "/pokedex/language/4/"
            },
            "version_group": {
                "name": "sword-shield",
                "url": "/pokedex/version-group/20/"
            }
        },
        {
            "flavor_text": "Apr\u00e8s son attaque, le lanceur revient \u00e0 toute vitesse\net change de place avec un Pok\u00e9mon de l\u2019\u00e9quipe\npr\u00eat au combat.",
            "language": {
                "name": "fr",
                "url": "/pokedex/language/5/"
            },
            "version_group": {
                "name": "sword-shield",
                "url": "/pokedex/version-group/20/"
            }
        },
        {
            "flavor_text": "Nach der Attacke eilt der Anwender zur\u00fcck und\ntauscht den Platz mit einem anderen Pok\u00e9mon.",
            "language": {
                "name": "de",
                "url": "/pokedex/language/6/"
            },
            "version_group": {
                "name": "sword-shield",
                "url": "/pokedex/version-group/20/"
            }
        },
        {
            "flavor_text": "Tras atacar, el usuario vuelve a toda prisa para dar paso\na otro Pok\u00e9mon del equipo.",
            "language": {
                "name": "es",
                "url": "/pokedex/language/7/"
            },
            "version_group": {
                "name": "sword-shield",
                "url": "/pokedex/version-group/20/"
            }
        },
        {
            "flavor_text": "Chi usa questa mossa fa marcia indietro per farsi\nsostituire dopo aver sferrato l\u2019attacco.",
            "language": {
                "name": "it",
                "url": "/pokedex/language/8/"
            },
            "version_group": {
                "name": "sword-shield",
                "url": "/pokedex/version-group/20/"
            }
        },
        {
            "flavor_text": "After making its attack, the user rushes back to\nswitch places with a party Pok\u00e9mon in waiting.",
            "language": {
                "name": "en",
                "url": "/pokedex/language/9/"
            },
            "version_group": {
                "name": "sword-shield",
                "url": "/pokedex/version-group/20/"
            }
        },
        {
            "flavor_text": "\u653b\u6483\u3057\u305f\u3042\u3068\n\u3082\u306e\u3059\u3054\u3044\u3000\u30b9\u30d4\u30fc\u30c9\u3067\u3000\u3082\u3069\u3063\u3066\u304d\u3066\n\u63a7\u3048\u306e\u3000\u30dd\u30b1\u30e2\u30f3\u3068\u3000\u5165\u308c\u66ff\u308f\u308b\u3002",
            "language": {
                "name": "ja",
                "url": "/pokedex/language/11/"
            },
            "version_group": {
                "name": "sword-shield",
                "url": "/pokedex/version-group/20/"
            }
        },
        {
            "flavor_text": "\u5728\u653b\u51fb\u4e4b\u540e\u6025\u901f\u8fd4\u56de\uff0c\n\u548c\u540e\u5907\u5b9d\u53ef\u68a6\u8fdb\u884c\u66ff\u6362\u3002",
            "language": {
                "name": "zh-Hans",
                "url": "/pokedex/language/12/"
            },
            "version_group": {
                "name": "sword-shield",
                "url": "/pokedex/version-group/20/"
            }
        }
    ],
    "generation": {
        "name": "generation-iv",
        "url": "/pokedex/generation/4/"
    },
    "id": 369,
    "learned_by_pokemon": [
        {
            "name": "butterfree",
            "url": "/pokedex/pokemon/12/"
        },
        {
            "name": "beedrill",
            "url": "/pokedex/pokemon/15/"
        },
        {
            "name": "pidgey",
            "url": "/pokedex/pokemon/16/"
        },
        {
            "name": "pidgeotto",
            "url": "/pokedex/pokemon/17/"
        },
        {
            "name": "pidgeot",
            "url": "/pokedex/pokemon/18/"
        },
        {
            "name": "rattata",
            "url": "/pokedex/pokemon/19/"
        },
        {
            "name": "raticate",
            "url": "/pokedex/pokemon/20/"
        },
        {
            "name": "spearow",
            "url": "/pokedex/pokemon/21/"
        },
        {
            "name": "fearow",
            "url": "/pokedex/pokemon/22/"
        },
        {
            "name": "zubat",
            "url": "/pokedex/pokemon/41/"
        },
        {
            "name": "golbat",
            "url": "/pokedex/pokemon/42/"
        },
        {
            "name": "venomoth",
            "url": "/pokedex/pokemon/49/"
        },
        {
            "name": "meowth",
            "url": "/pokedex/pokemon/52/"
        },
        {
            "name": "persian",
            "url": "/pokedex/pokemon/53/"
        },
        {
            "name": "mankey",
            "url": "/pokedex/pokemon/56/"
        },
        {
            "name": "primeape",
            "url": "/pokedex/pokemon/57/"
        },
        {
            "name": "farfetchd",
            "url": "/pokedex/pokemon/83/"
        },
        {
            "name": "scyther",
            "url": "/pokedex/pokemon/123/"
        },
        {
            "name": "articuno",
            "url": "/pokedex/pokemon/144/"
        },
        {
            "name": "zapdos",
            "url": "/pokedex/pokemon/145/"
        },
        {
            "name": "moltres",
            "url": "/pokedex/pokemon/146/"
        },
        {
            "name": "mew",
            "url": "/pokedex/pokemon/151/"
        },
        {
            "name": "sentret",
            "url": "/pokedex/pokemon/161/"
        },
        {
            "name": "furret",
            "url": "/pokedex/pokemon/162/"
        },
        {
            "name": "ledyba",
            "url": "/pokedex/pokemon/165/"
        },
        {
            "name": "ledian",
            "url": "/pokedex/pokemon/166/"
        },
        {
            "name": "crobat",
            "url": "/pokedex/pokemon/169/"
        },
        {
            "name": "natu",
            "url": "/pokedex/pokemon/177/"
        },
        {
            "name": "xatu",
            "url": "/pokedex/pokemon/178/"
        },
        {
            "name": "hoppip",
            "url": "/pokedex/pokemon/187/"
        },
        {
            "name": "skiploom",
            "url": "/pokedex/pokemon/188/"
        },
        {
            "name": "jumpluff",
            "url": "/pokedex/pokemon/189/"
        },
        {
            "name": "aipom",
            "url": "/pokedex/pokemon/190/"
        },
        {
            "name": "yanma",
            "url": "/pokedex/pokemon/193/"
        },
        {
            "name": "murkrow",
            "url": "/pokedex/pokemon/198/"
        },
        {
            "name": "gligar",
            "url": "/pokedex/pokemon/207/"
        },
        {
            "name": "scizor",
            "url": "/pokedex/pokemon/212/"
        },
        {
            "name": "celebi",
            "url": "/pokedex/pokemon/251/"
        },
        {
            "name": "blaziken",
            "url": "/pokedex/pokemon/257/"
        },
        {
            "name": "beautifly",
            "url": "/pokedex/pokemon/267/"
        },
        {
            "name": "dustox",
            "url": "/pokedex/pokemon/269/"
        },
        {
            "name": "taillow",
            "url": "/pokedex/pokemon/276/"
        },
        {
            "name": "swellow",
            "url": "/pokedex/pokemon/277/"
        },
        {
            "name": "wingull",
            "url": "/pokedex/pokemon/278/"
        },
        {
            "name": "pelipper",
            "url": "/pokedex/pokemon/279/"
        },
        {
            "name": "masquerain",
            "url": "/pokedex/pokemon/284/"
        },
        {
            "name": "ninjask",
            "url": "/pokedex/pokemon/291/"
        },
        {
            "name": "volbeat",
            "url": "/pokedex/pokemon/313/"
        },
        {
            "name": "illumise",
            "url": "/pokedex/pokemon/314/"
        },
        {
            "name": "vibrava",
            "url": "/pokedex/pokemon/329/"
        },
        {
            "name": "flygon",
            "url": "/pokedex/pokemon/330/"
        },
        {
            "name": "tropius",
            "url": "/pokedex/pokemon/357/"
        },
        {
            "name": "rayquaza",
            "url": "/pokedex/pokemon/384/"
        },
        {
            "name": "jirachi",
            "url": "/pokedex/pokemon/385/"
        },
        {
            "name": "chimchar",
            "url": "/pokedex/pokemon/390/"
        },
        {
            "name": "monferno",
            "url": "/pokedex/pokemon/391/"
        },
        {
            "name": "infernape",
            "url": "/pokedex/pokemon/392/"
        },
        {
            "name": "starly",
            "url": "/pokedex/pokemon/396/"
        },
        {
            "name": "staravia",
            "url": "/pokedex/pokemon/397/"
        },
        {
            "name": "staraptor",
            "url": "/pokedex/pokemon/398/"
        },
        {
            "name": "mothim",
            "url": "/pokedex/pokemon/414/"
        },
        {
            "name": "vespiquen",
            "url": "/pokedex/pokemon/416/"
        },
        {
            "name": "pachirisu",
            "url": "/pokedex/pokemon/417/"
        },
        {
            "name": "ambipom",
            "url": "/pokedex/pokemon/424/"
        },
        {
            "name": "lopunny",
            "url": "/pokedex/pokemon/428/"
        },
        {
            "name": "honchkrow",
            "url": "/pokedex/pokemon/430/"
        },
        {
            "name": "glameow",
            "url": "/pokedex/pokemon/431/"
        },
        {
            "name": "purugly",
            "url": "/pokedex/pokemon/432/"
        },
        {
            "name": "chatot",
            "url": "/pokedex/pokemon/441/"
        },
        {
            "name": "finneon",
            "url": "/pokedex/pokemon/456/"
        },
        {
            "name": "lumineon",
            "url": "/pokedex/pokemon/457/"
        },
        {
            "name": "yanmega",
            "url": "/pokedex/pokemon/469/"
        },
        {
            "name": "gliscor",
            "url": "/pokedex/pokemon/472/"
        },
        {
            "name": "uxie",
            "url": "/pokedex/pokemon/480/"
        },
        {
            "name": "mesprit",
            "url": "/pokedex/pokemon/481/"
        },
        {
            "name": "azelf",
            "url": "/pokedex/pokemon/482/"
        },
        {
            "name": "phione",
            "url": "/pokedex/pokemon/489/"
        },
        {
            "name": "manaphy",
            "url": "/pokedex/pokemon/490/"
        },
        {
            "name": "victini",
            "url": "/pokedex/pokemon/494/"
        },
        {
            "name": "purrloin",
            "url": "/pokedex/pokemon/509/"
        },
        {
            "name": "liepard",
            "url": "/pokedex/pokemon/510/"
        },
        {
            "name": "pidove",
            "url": "/pokedex/pokemon/519/"
        },
        {
            "name": "tranquill",
            "url": "/pokedex/pokemon/520/"
        },
        {
            "name": "unfezant",
            "url": "/pokedex/pokemon/521/"
        },
        {
            "name": "woobat",
            "url": "/pokedex/pokemon/527/"
        },
        {
            "name": "swoobat",
            "url": "/pokedex/pokemon/528/"
        },
        {
            "name": "whimsicott",
            "url": "/pokedex/pokemon/547/"
        },
        {
            "name": "darumaka",
            "url": "/pokedex/pokemon/554/"
        },
        {
            "name": "darmanitan-standard",
            "url": "/pokedex/pokemon/555/"
        },
        {
            "name": "archen",
            "url": "/pokedex/pokemon/566/"
        },
        {
            "name": "archeops",
            "url": "/pokedex/pokemon/567/"
        },
        {
            "name": "zorua",
            "url": "/pokedex/pokemon/570/"
        },
        {
            "name": "zoroark",
            "url": "/pokedex/pokemon/571/"
        },
        {
            "name": "minccino",
            "url": "/pokedex/pokemon/572/"
        },
        {
            "name": "cinccino",
            "url": "/pokedex/pokemon/573/"
        },
        {
            "name": "emolga",
            "url": "/pokedex/pokemon/587/"
        },
        {
            "name": "eelektrik",
            "url": "/pokedex/pokemon/603/"
        },
        {
            "name": "eelektross",
            "url": "/pokedex/pokemon/604/"
        },
        {
            "name": "accelgor",
            "url": "/pokedex/pokemon/617/"
        },
        {
            "name": "mienfoo",
            "url": "/pokedex/pokemon/619/"
        },
        {
            "name": "mienshao",
            "url": "/pokedex/pokemon/620/"
        },
        {
            "name": "rufflet",
            "url": "/pokedex/pokemon/627/"
        },
        {
            "name": "braviary",
            "url": "/pokedex/pokemon/628/"
        },
        {
            "name": "vullaby",
            "url": "/pokedex/pokemon/629/"
        },
        {
            "name": "mandibuzz",
            "url": "/pokedex/pokemon/630/"
        },
        {
            "name": "hydreigon",
            "url": "/pokedex/pokemon/635/"
        },
        {
            "name": "larvesta",
            "url": "/pokedex/pokemon/636/"
        },
        {
            "name": "volcarona",
            "url": "/pokedex/pokemon/637/"
        },
        {
            "name": "tornadus-incarnate",
            "url": "/pokedex/pokemon/641/"
        },
        {
            "name": "thundurus-incarnate",
            "url": "/pokedex/pokemon/642/"
        },
        {
            "name": "landorus-incarnate",
            "url": "/pokedex/pokemon/645/"
        },
        {
            "name": "meloetta-aria",
            "url": "/pokedex/pokemon/648/"
        },
        {
            "name": "genesect",
            "url": "/pokedex/pokemon/649/"
        },
        {
            "name": "froakie",
            "url": "/pokedex/pokemon/656/"
        },
        {
            "name": "frogadier",
            "url": "/pokedex/pokemon/657/"
        },
        {
            "name": "greninja",
            "url": "/pokedex/pokemon/658/"
        },
        {
            "name": "bunnelby",
            "url": "/pokedex/pokemon/659/"
        },
        {
            "name": "diggersby",
            "url": "/pokedex/pokemon/660/"
        },
        {
            "name": "fletchling",
            "url": "/pokedex/pokemon/661/"
        },
        {
            "name": "fletchinder",
            "url": "/pokedex/pokemon/662/"
        },
        {
            "name": "talonflame",
            "url": "/pokedex/pokemon/663/"
        },
        {
            "name": "vivillon",
            "url": "/pokedex/pokemon/666/"
        },
        {
            "name": "furfrou",
            "url": "/pokedex/pokemon/676/"
        },
        {
            "name": "clauncher",
            "url": "/pokedex/pokemon/692/"
        },
        {
            "name": "clawitzer",
            "url": "/pokedex/pokemon/693/"
        },
        {
            "name": "helioptile",
            "url": "/pokedex/pokemon/694/"
        },
        {
            "name": "heliolisk",
            "url": "/pokedex/pokemon/695/"
        },
        {
            "name": "hawlucha",
            "url": "/pokedex/pokemon/701/"
        },
        {
            "name": "dedenne",
            "url": "/pokedex/pokemon/702/"
        },
        {
            "name": "noibat",
            "url": "/pokedex/pokemon/714/"
        },
        {
            "name": "noivern",
            "url": "/pokedex/pokemon/715/"
        },
        {
            "name": "yveltal",
            "url": "/pokedex/pokemon/717/"
        },
        {
            "name": "decidueye",
            "url": "/pokedex/pokemon/724/"
        },
        {
            "name": "litten",
            "url": "/pokedex/pokemon/725/"
        },
        {
            "name": "torracat",
            "url": "/pokedex/pokemon/726/"
        },
        {
            "name": "incineroar",
            "url": "/pokedex/pokemon/727/"
        },
        {
            "name": "pikipek",
            "url": "/pokedex/pokemon/731/"
        },
        {
            "name": "trumbeak",
            "url": "/pokedex/pokemon/732/"
        },
        {
            "name": "toucannon",
            "url": "/pokedex/pokemon/733/"
        },
        {
            "name": "yungoos",
            "url": "/pokedex/pokemon/734/"
        },
        {
            "name": "gumshoos",
            "url": "/pokedex/pokemon/735/"
        },
        {
            "name": "oricorio-baile",
            "url": "/pokedex/pokemon/741/"
        },
        {
            "name": "cutiefly",
            "url": "/pokedex/pokemon/742/"
        },
        {
            "name": "ribombee",
            "url": "/pokedex/pokemon/743/"
        },
        {
            "name": "wishiwashi-solo",
            "url": "/pokedex/pokemon/746/"
        },
        {
            "name": "tsareena",
            "url": "/pokedex/pokemon/763/"
        },
        {
            "name": "comfey",
            "url": "/pokedex/pokemon/764/"
        },
        {
            "name": "passimian",
            "url": "/pokedex/pokemon/766/"
        },
        {
            "name": "type-null",
            "url": "/pokedex/pokemon/772/"
        },
        {
            "name": "silvally",
            "url": "/pokedex/pokemon/773/"
        },
        {
            "name": "minior-red-meteor",
            "url": "/pokedex/pokemon/774/"
        },
        {
            "name": "komala",
            "url": "/pokedex/pokemon/775/"
        },
        {
            "name": "togedemaru",
            "url": "/pokedex/pokemon/777/"
        },
        {
            "name": "tapu-koko",
            "url": "/pokedex/pokemon/785/"
        },
        {
            "name": "pheromosa",
            "url": "/pokedex/pokemon/795/"
        },
        {
            "name": "naganadel",
            "url": "/pokedex/pokemon/804/"
        },
        {
            "name": "grookey",
            "url": "/pokedex/pokemon/810/"
        },
        {
            "name": "thwackey",
            "url": "/pokedex/pokemon/811/"
        },
        {
            "name": "rillaboom",
            "url": "/pokedex/pokemon/812/"
        },
        {
            "name": "scorbunny",
            "url": "/pokedex/pokemon/813/"
        },
        {
            "name": "raboot",
            "url": "/pokedex/pokemon/814/"
        },
        {
            "name": "cinderace",
            "url": "/pokedex/pokemon/815/"
        },
        {
            "name": "sobble",
            "url": "/pokedex/pokemon/816/"
        },
        {
            "name": "drizzile",
            "url": "/pokedex/pokemon/817/"
        },
        {
            "name": "inteleon",
            "url": "/pokedex/pokemon/818/"
        },
        {
            "name": "rookidee",
            "url": "/pokedex/pokemon/821/"
        },
        {
            "name": "corvisquire",
            "url": "/pokedex/pokemon/822/"
        },
        {
            "name": "corviknight",
            "url": "/pokedex/pokemon/823/"
        },
        {
            "name": "orbeetle",
            "url": "/pokedex/pokemon/826/"
        },
        {
            "name": "thievul",
            "url": "/pokedex/pokemon/828/"
        },
        {
            "name": "flapple",
            "url": "/pokedex/pokemon/841/"
        },
        {
            "name": "perrserker",
            "url": "/pokedex/pokemon/863/"
        },
        {
            "name": "frosmoth",
            "url": "/pokedex/pokemon/873/"
        },
        {
            "name": "drakloak",
            "url": "/pokedex/pokemon/886/"
        },
        {
            "name": "dragapult",
            "url": "/pokedex/pokemon/887/"
        },
        {
            "name": "kubfu",
            "url": "/pokedex/pokemon/891/"
        },
        {
            "name": "urshifu-single-strike",
            "url": "/pokedex/pokemon/892/"
        },
        {
            "name": "zarude",
            "url": "/pokedex/pokemon/893/"
        },
        {
            "name": "kleavor",
            "url": "/pokedex/pokemon/900/"
        },
        {
            "name": "sneasler",
            "url": "/pokedex/pokemon/903/"
        },
        {
            "name": "sprigatito",
            "url": "/pokedex/pokemon/906/"
        },
        {
            "name": "floragato",
            "url": "/pokedex/pokemon/907/"
        },
        {
            "name": "meowscarada",
            "url": "/pokedex/pokemon/908/"
        },
        {
            "name": "quaquaval",
            "url": "/pokedex/pokemon/914/"
        },
        {
            "name": "spidops",
            "url": "/pokedex/pokemon/918/"
        },
        {
            "name": "nymble",
            "url": "/pokedex/pokemon/919/"
        },
        {
            "name": "lokix",
            "url": "/pokedex/pokemon/920/"
        },
        {
            "name": "tandemaus",
            "url": "/pokedex/pokemon/924/"
        },
        {
            "name": "maushold",
            "url": "/pokedex/pokemon/925/"
        },
        {
            "name": "squawkabilly",
            "url": "/pokedex/pokemon/931/"
        },
        {
            "name": "wattrel",
            "url": "/pokedex/pokemon/940/"
        },
        {
            "name": "kilowattrel",
            "url": "/pokedex/pokemon/941/"
        },
        {
            "name": "shroodle",
            "url": "/pokedex/pokemon/944/"
        },
        {
            "name": "grafaiai",
            "url": "/pokedex/pokemon/945/"
        },
        {
            "name": "flittle",
            "url": "/pokedex/pokemon/955/"
        },
        {
            "name": "espathra",
            "url": "/pokedex/pokemon/956/"
        },
        {
            "name": "bombirdier",
            "url": "/pokedex/pokemon/962/"
        },
        {
            "name": "cyclizar",
            "url": "/pokedex/pokemon/967/"
        },
        {
            "name": "flamigo",
            "url": "/pokedex/pokemon/973/"
        },
        {
            "name": "annihilape",
            "url": "/pokedex/pokemon/979/"
        },
        {
            "name": "slither-wing",
            "url": "/pokedex/pokemon/988/"
        },
        {
            "name": "iron-bundle",
            "url": "/pokedex/pokemon/991/"
        },
        {
            "name": "iron-jugulis",
            "url": "/pokedex/pokemon/993/"
        },
        {
            "name": "iron-moth",
            "url": "/pokedex/pokemon/994/"
        },
        {
            "name": "roaring-moon",
            "url": "/pokedex/pokemon/1005/"
        },
        {
            "name": "koraidon",
            "url": "/pokedex/pokemon/1007/"
        },
        {
            "name": "miraidon",
            "url": "/pokedex/pokemon/1008/"
        },
        {
            "name": "darmanitan-zen",
            "url": "/pokedex/pokemon/10017/"
        },
        {
            "name": "meloetta-pirouette",
            "url": "/pokedex/pokemon/10018/"
        },
        {
            "name": "tornadus-therian",
            "url": "/pokedex/pokemon/10019/"
        },
        {
            "name": "thundurus-therian",
            "url": "/pokedex/pokemon/10020/"
        },
        {
            "name": "landorus-therian",
            "url": "/pokedex/pokemon/10021/"
        },
        {
            "name": "scizor-mega",
            "url": "/pokedex/pokemon/10046/"
        },
        {
            "name": "pidgeot-mega",
            "url": "/pokedex/pokemon/10073/"
        },
        {
            "name": "beedrill-mega",
            "url": "/pokedex/pokemon/10090/"
        },
        {
            "name": "rattata-alola",
            "url": "/pokedex/pokemon/10091/"
        },
        {
            "name": "raticate-alola",
            "url": "/pokedex/pokemon/10092/"
        },
        {
            "name": "raticate-totem-alola",
            "url": "/pokedex/pokemon/10093/"
        },
        {
            "name": "meowth-alola",
            "url": "/pokedex/pokemon/10107/"
        },
        {
            "name": "persian-alola",
            "url": "/pokedex/pokemon/10108/"
        },
        {
            "name": "greninja-battle-bond",
            "url": "/pokedex/pokemon/10116/"
        },
        {
            "name": "greninja-ash",
            "url": "/pokedex/pokemon/10117/"
        },
        {
            "name": "gumshoos-totem",
            "url": "/pokedex/pokemon/10121/"
        },
        {
            "name": "oricorio-pom-pom",
            "url": "/pokedex/pokemon/10123/"
        },
        {
            "name": "oricorio-pau",
            "url": "/pokedex/pokemon/10124/"
        },
        {
            "name": "oricorio-sensu",
            "url": "/pokedex/pokemon/10125/"
        },
        {
            "name": "wishiwashi-school",
            "url": "/pokedex/pokemon/10127/"
        },
        {
            "name": "minior-orange-meteor",
            "url": "/pokedex/pokemon/10130/"
        },
        {
            "name": "minior-yellow-meteor",
            "url": "/pokedex/pokemon/10131/"
        },
        {
            "name": "minior-green-meteor",
            "url": "/pokedex/pokemon/10132/"
        },
        {
            "name": "minior-blue-meteor",
            "url": "/pokedex/pokemon/10133/"
        },
        {
            "name": "minior-indigo-meteor",
            "url": "/pokedex/pokemon/10134/"
        },
        {
            "name": "minior-violet-meteor",
            "url": "/pokedex/pokemon/10135/"
        },
        {
            "name": "minior-red",
            "url": "/pokedex/pokemon/10136/"
        },
        {
            "name": "minior-orange",
            "url": "/pokedex/pokemon/10137/"
        },
        {
            "name": "minior-yellow",
            "url": "/pokedex/pokemon/10138/"
        },
        {
            "name": "minior-green",
            "url": "/pokedex/pokemon/10139/"
        },
        {
            "name": "minior-blue",
            "url": "/pokedex/pokemon/10140/"
        },
        {
            "name": "minior-indigo",
            "url": "/pokedex/pokemon/10141/"
        },
        {
            "name": "minior-violet",
            "url": "/pokedex/pokemon/10142/"
        },
        {
            "name": "ribombee-totem",
            "url": "/pokedex/pokemon/10150/"
        },
        {
            "name": "togedemaru-totem",
            "url": "/pokedex/pokemon/10154/"
        },
        {
            "name": "meowth-galar",
            "url": "/pokedex/pokemon/10161/"
        },
        {
            "name": "articuno-galar",
            "url": "/pokedex/pokemon/10169/"
        },
        {
            "name": "zapdos-galar",
            "url": "/pokedex/pokemon/10170/"
        },
        {
            "name": "moltres-galar",
            "url": "/pokedex/pokemon/10171/"
        },
        {
            "name": "darumaka-galar",
            "url": "/pokedex/pokemon/10176/"
        },
        {
            "name": "darmanitan-galar-standard",
            "url": "/pokedex/pokemon/10177/"
        },
        {
            "name": "darmanitan-galar-zen",
            "url": "/pokedex/pokemon/10178/"
        },
        {
            "name": "urshifu-rapid-strike",
            "url": "/pokedex/pokemon/10191/"
        },
        {
            "name": "zarude-dada",
            "url": "/pokedex/pokemon/10192/"
        },
        {
            "name": "zorua-hisui",
            "url": "/pokedex/pokemon/10238/"
        },
        {
            "name": "zoroark-hisui",
            "url": "/pokedex/pokemon/10239/"
        },
        {
            "name": "braviary-hisui",
            "url": "/pokedex/pokemon/10240/"
        },
        {
            "name": "decidueye-hisui",
            "url": "/pokedex/pokemon/10244/"
        },
        {
            "name": "maushold-family-of-three",
            "url": "/pokedex/pokemon/10257/"
        },
        {
            "name": "squawkabilly-blue-plumage",
            "url": "/pokedex/pokemon/10260/"
        },
        {
            "name": "squawkabilly-yellow-plumage",
            "url": "/pokedex/pokemon/10261/"
        },
        {
            "name": "squawkabilly-white-plumage",
            "url": "/pokedex/pokemon/10262/"
        },
        {
            "name": "koraidon-limited-build",
            "url": "/pokedex/pokemon/10264/"
        },
        {
            "name": "koraidon-sprinting-build",
            "url": "/pokedex/pokemon/10265/"
        },
        {
            "name": "koraidon-swimming-build",
            "url": "/pokedex/pokemon/10266/"
        },
        {
            "name": "koraidon-gliding-build",
            "url": "/pokedex/pokemon/10267/"
        },
        {
            "name": "miraidon-low-power-mode",
            "url": "/pokedex/pokemon/10268/"
        },
        {
            "name": "miraidon-drive-mode",
            "url": "/pokedex/pokemon/10269/"
        },
        {
            "name": "miraidon-aquatic-mode",
            "url": "/pokedex/pokemon/10270/"
        },
        {
            "name": "miraidon-glide-mode",
            "url": "/pokedex/pokemon/10271/"
        }
    ],
    "machines": [
        {
            "machine": {
                "url": "/pokedex/machine/360/"
            },
            "version_group": {
                "name": "lets-go-pikachu-lets-go-eevee",
                "url": "/pokedex/version-group/19/"
            }
        },
        {
            "machine": {
                "url": "/pokedex/machine/1067/"
            },
            "version_group": {
                "name": "sword-shield",
                "url": "/pokedex/version-group/20/"
            }
        },
        {
            "machine": {
                "url": "/pokedex/machine/1392/"
            },
            "version_group": {
                "name": "diamond-pearl",
                "url": "/pokedex/version-group/8/"
            }
        },
        {
            "machine": {
                "url": "/pokedex/machine/1393/"
            },
            "version_group": {
                "name": "platinum",
                "url": "/pokedex/version-group/9/"
            }
        },
        {
            "machine": {
                "url": "/pokedex/machine/1394/"
            },
            "version_group": {
                "name": "heartgold-soulsilver",
                "url": "/pokedex/version-group/10/"
            }
        },
        {
            "machine": {
                "url": "/pokedex/machine/1395/"
            },
            "version_group": {
                "name": "black-white",
                "url": "/pokedex/version-group/11/"
            }
        },
        {
            "machine": {
                "url": "/pokedex/machine/1396/"
            },
            "version_group": {
                "name": "black-2-white-2",
                "url": "/pokedex/version-group/14/"
            }
        },
        {
            "machine": {
                "url": "/pokedex/machine/1397/"
            },
            "version_group": {
                "name": "x-y",
                "url": "/pokedex/version-group/15/"
            }
        },
        {
            "machine": {
                "url": "/pokedex/machine/1398/"
            },
            "version_group": {
                "name": "omega-ruby-alpha-sapphire",
                "url": "/pokedex/version-group/16/"
            }
        },
        {
            "machine": {
                "url": "/pokedex/machine/1399/"
            },
            "version_group": {
                "name": "sun-moon",
                "url": "/pokedex/version-group/17/"
            }
        },
        {
            "machine": {
                "url": "/pokedex/machine/1400/"
            },
            "version_group": {
                "name": "ultra-sun-ultra-moon",
                "url": "/pokedex/version-group/18/"
            }
        }
    ],
    "meta": {
        "ailment": {
            "name": "none",
            "url": "/pokedex/move-ailment/0/"
        },
        "ailment_chance": 0,
        "category": {
            "name": "damage",
            "url": "/pokedex/move-category/0/"
        },
        "crit_rate": 0,
        "drain": 0,
        "flinch_chance": 0,
        "healing": 0,
        "max_hits": null,
        "max_turns": null,
        "min_hits": null,
        "min_turns": null,
        "stat_chance": 0
    },
    "name": "u-turn",
    "names": [
        {
            "language": {
                "name": "ja-Hrkt",
                "url": "/pokedex/language/1/"
            },
            "name": "\u3068\u3093\u307c\u304c\u3048\u308a"
        },
        {
            "language": {
                "name": "ko",
                "url": "/pokedex/language/3/"
            },
            "name": "\uc720\ud134"
        },
        {
            "language": {
                "name": "zh-Hant",
                "url": "/pokedex/language/4/"
            },
            "name": "\u6025\u901f\u6298\u8fd4"
        },
        {
            "language": {
                "name": "fr",
                "url": "/pokedex/language/5/"
            },
            "name": "Demi-Tour"
        },
        {
            "language": {
                "name": "de",
                "url": "/pokedex/language/6/"
            },
            "name": "Kehrtwende"
        },
        {
            "language": {
                "name": "es",
                "url": "/pokedex/language/7/"
            },
            "name": "Ida y Vuelta"
        },
        {
            "language": {
                "name": "it",
                "url": "/pokedex/language/8/"
            },
            "name": "Retromarcia"
        },
        {
            "language": {
                "name": "en",
                "url": "/pokedex/language/9/"
            },
            "name": "U-turn"
        },
        {
            "language": {
                "name": "ja",
                "url": "/pokedex/language/11/"
            },
            "name": "\u3068\u3093\u307c\u304c\u3048\u308a"
        },
        {
            "language": {
                "name": "zh-Hans",
                "url": "/pokedex/language/12/"
            },
            "name": "\u6025\u901f\u6298\u8fd4"
        }
    ],
    "past_values": [],
    "power": 70,
    "pp": 20,
    "priority": 0,
    "stat_changes": [],
    "super_contest_effect": {
        "url": "/pokedex/super-contest-effect/16/"
    },
    "target": {
        "name": "selected-pokemon",
        "url": "/pokedex/move-target/10/"
    },
    "type": {
        "name": "bug",
        "url": "/pokedex/type/7/"
    }
}