{
    "accuracy": 100,
    "contest_combos": {
        "normal": {
            "use_after": [
                {
                    "name": "lock-on",
                    "url": "/pokedex/move/199/"
                }
            ],
            "use_before": null
        },
        "super": {
            "use_after": null,
            "use_before": null
        }
    },
    "contest_effect": {
        "url": "/pokedex/contest-effect/8/"
    },
    "contest_type": {
        "name": "beauty",
        "url": "/pokedex/contest-type/2/"
    },
    "damage_class": {
        "name": "special",
        "url": "/pokedex/move-damage-class/3/"
    },
    "effect_chance": 20,
    "effect_changes": [],
    "effect_entries": [
        {
            "effect": "Inflicts regular damage.  Has a $effect_chance% chance to burn, freeze, or paralyze the target.  One of these effects is selected at random; they do not each have independent chances to occur.",
            "language": {
                "name": "en",
                "url": "/pokedex/language/9/"
            },
            "short_effect": "Has a $effect_chance% chance to burn, freeze, or paralyze the target."
        }
    ],
    "flavor_text_entries": [
        {
            "flavor_text": "Fires three kinds\nof beams at once.",
            "language": {
                "name": "en",
                "url": "/pokedex/language/9/"
            },
            "version_group": {
                "name": "gold-silver",
                "url": "/pokedex/version-group/3/"
            }
        },
        {
            "flavor_text": "Fires three kinds\nof beams at once.",
            "language": {
                "name": "en",
                "url": "/pokedex/language/9/"
            },
            "version_group": {
                "name": "crystal",
                "url": "/pokedex/version-group/4/"
            }
        },
        {
            "flavor_text": "Fires three types of beams\nat the same time.",
            "language": {
                "name": "en",
                "url": "/pokedex/language/9/"
            },
            "version_group": {
                "name": "ruby-sapphire",
                "url": "/pokedex/version-group/5/"
            }
        },
        {
            "flavor_text": "Fires three types of beams\nat the same time.",
            "language": {
                "name": "en",
                "url": "/pokedex/language/9/"
            },
            "version_group": {
                "name": "emerald",
                "url": "/pokedex/version-group/6/"
            }
        },
        {
            "flavor_text": "A simultaneous\n3-beam attack that\nmay paralyze, burn,\nor freeze the foe.",
            "language": {
                "name": "en",
                "url": "/pokedex/language/9/"
            },
            "version_group": {
                "name": "firered-leafgreen",
                "url": "/pokedex/version-group/7/"
            }
        },
        {
            "flavor_text": "The user strikes with\na simultaneous three-\nbeam attack. May also\nparalyze, burn, or\nfreeze the target.",
            "language": {
                "name": "en",
                "url": "/pokedex/language/9/"
            },
            "version_group": {
                "name": "diamond-pearl",
                "url": "/pokedex/version-group/8/"
            }
        },
        {
            "flavor_text": "The user strikes with\na simultaneous three-\nbeam attack. May also\nparalyze, burn, or\nfreeze the target.",
            "language": {
                "name": "en",
                "url": "/pokedex/language/9/"
            },
            "version_group": {
                "name": "platinum",
                "url": "/pokedex/version-group/9/"
            }
        },
        {
            "flavor_text": "The user strikes with\na simultaneous three-\nbeam attack. May also\nparalyze, burn, or\nfreeze the target.",
            "language": {
                "name": "en",
                "url": "/pokedex/language/9/"
            },
            "version_group": {
                "name": "heartgold-soulsilver",
                "url": "/pokedex/version-group/10/"
            }
        },
        {
            "flavor_text": "Le lanceur envoie trois boules d\u2019\u00e9nergie\nsimultan\u00e9ment. Peut aussi paralyser,\nbr\u00fbler ou geler l\u2019ennemi.",
            "language": {
                "name": "fr",
                "url": "/pokedex/language/5/"
            },
            "version_group": {
                "name": "black-white",
                "url": "/pokedex/version-group/11/"
            }
        },
        {
            "flavor_text": "The user strikes with a simultaneous\nthree-beam attack. May also burn, freeze,\nor leave the target with paralysis.",
            "language": {
                "name": "en",
                "url": "/pokedex/language/9/"
            },
            "version_group": {
                "name": "black-white",
                "url": "/pokedex/version-group/11/"
            }
        },
        {
            "flavor_text": "The user strikes with a simultaneous\nthree-beam attack. May also burn, freeze,\nor leave the target with paralysis.",
            "language": {
                "name": "en",
                "url": "/pokedex/language/9/"
            },
            "version_group": {
                "name": "black-2-white-2",
                "url": "/pokedex/version-group/14/"
            }
        },
        {
            "flavor_text": "\uff13\u3064\u306e\u3000\u3053\u3046\u305b\u3093\u3067\u3000\u3053\u3046\u3052\u304d\u3059\u308b\u3002\n\u307e\u3072\u304b\u3000\u3084\u3051\u3069\u304b\u3000\u3053\u304a\u308a\u3058\u3087\u3046\u305f\u3044\u306e\n\u3069\u308c\u304b\u306b\u3000\u3059\u308b\u3053\u3068\u304c\u3000\u3042\u308b\u3002",
            "language": {
                "name": "ja-Hrkt",
                "url": "/pokedex/language/1/"
            },
            "version_group": {
                "name": "x-y",
                "url": "/pokedex/version-group/15/"
            }
        },
        {
            "flavor_text": "3\uac1c\uc758 \uad11\uc120\uc73c\ub85c \uacf5\uaca9\ud55c\ub2e4.\n\ub9c8\ube44, \ud654\uc0c1 \ub610\ub294 \uc5bc\uc74c \uc0c1\ud0dc \uc911\n\uc5b4\ub290 \ud558\ub098\ub85c \ub9cc\ub4e4 \ub54c\uac00 \uc788\ub2e4.",
            "language": {
                "name": "ko",
                "url": "/pokedex/language/3/"
            },
            "version_group": {
                "name": "x-y",
                "url": "/pokedex/version-group/15/"
            }
        },
        {
            "flavor_text": "Le lanceur envoie trois boules d\u2019\u00e9nergie\nsimultan\u00e9ment. Peut aussi paralyser, br\u00fbler ou\ngeler l\u2019ennemi.",
            "language": {
                "name": "fr",
                "url": "/pokedex/language/5/"
            },
            "version_group": {
                "name": "x-y",
                "url": "/pokedex/version-group/15/"
            }
        },
        {
            "flavor_text": "Feuert drei Strahlen ab. Verursacht eventuell\nParalyse, Verbrennung oder Einfrieren.",
            "language": {
                "name": "de",
                "url": "/pokedex/language/6/"
            },
            "version_group": {
                "name": "x-y",
                "url": "/pokedex/version-group/15/"
            }
        },
        {
            "flavor_text": "Ataque triple que puede paralizar, quemar o\ncongelar al objetivo.",
            "language": {
                "name": "es",
                "url": "/pokedex/language/7/"
            },
            "version_group": {
                "name": "x-y",
                "url": "/pokedex/version-group/15/"
            }
        },
        {
            "flavor_text": "Colpisce il bersaglio con tre sfere simultanee che\npossono paralizzarlo, scottarlo o congelarlo.",
            "language": {
                "name": "it",
                "url": "/pokedex/language/8/"
            },
            "version_group": {
                "name": "x-y",
                "url": "/pokedex/version-group/15/"
            }
        },
        {
            "flavor_text": "The user strikes with a simultaneous\nthree-beam attack. May also burn, freeze,\nor leave the target with paralysis.",
            "language": {
                "name": "en",
                "url": "/pokedex/language/9/"
            },
            "version_group": {
                "name": "x-y",
                "url": "/pokedex/version-group/15/"
            }
        },
        {
            "flavor_text": "\uff13\u3064\u306e\u3000\u5149\u7dda\u3067\u3000\u653b\u6483\u3059\u308b\u3002\n\u307e\u3072\u304b\u3000\u3084\u3051\u3069\u304b\u3000\u3053\u304a\u308a\u72b6\u614b\u306e\n\u3069\u308c\u304b\u306b\u3000\u3059\u308b\u3053\u3068\u304c\u3000\u3042\u308b\u3002",
            "language": {
                "name": "ja",
                "url": "/pokedex/language/11/"
            },
            "version_group": {
                "name": "x-y",
                "url": "/pokedex/version-group/15/"
            }
        },
        {
            "flavor_text": "\uff13\u3064\u306e\u3000\u3053\u3046\u305b\u3093\u3067\u3000\u3053\u3046\u3052\u304d\u3059\u308b\u3002\n\u307e\u3072\u304b\u3000\u3084\u3051\u3069\u304b\u3000\u3053\u304a\u308a\u3058\u3087\u3046\u305f\u3044\u306e\n\u3069\u308c\u304b\u306b\u3000\u3059\u308b\u3053\u3068\u304c\u3000\u3042\u308b\u3002",
            "language": {
                "name": "ja-Hrkt",
                "url": "/pokedex/language/1/"
            },
            "version_group": {
                "name": "omega-ruby-alpha-sapphire",
                "url": "/pokedex/version-group/16/"
            }
        },
        {
            "flavor_text": "3\uac1c\uc758 \uad11\uc120\uc73c\ub85c \uacf5\uaca9\ud55c\ub2e4.\n\ub9c8\ube44, \ud654\uc0c1 \ub610\ub294 \uc5bc\uc74c \uc0c1\ud0dc \uc911\n\uc5b4\ub290 \ud558\ub098\ub85c \ub9cc\ub4e4 \ub54c\uac00 \uc788\ub2e4.",
            "language": {
                "name": "ko",
                "url": "/pokedex/language/3/"
            },
            "version_group": {
                "name": "omega-ruby-alpha-sapphire",
                "url": "/pokedex/version-group/16/"
            }
        },
        {
            "flavor_text": "Le lanceur envoie trois boules d\u2019\u00e9nergie\nsimultan\u00e9ment. Peut aussi paralyser, br\u00fbler ou\ngeler l\u2019ennemi.",
            "language": {
                "name": "fr",
                "url": "/pokedex/language/5/"
            },
            "version_group": {
                "name": "omega-ruby-alpha-sapphire",
                "url": "/pokedex/version-group/16/"
            }
        },
        {
            "flavor_text": "Feuert drei Strahlen ab. Verursacht eventuell\nParalyse, Verbrennung oder Einfrieren.",
            "language": {
                "name": "de",
                "url": "/pokedex/language/6/"
            },
            "version_group": {
                "name": "omega-ruby-alpha-sapphire",
                "url": "/pokedex/version-group/16/"
            }
        },
        {
            "flavor_text": "Ataque triple que puede paralizar, quemar o congelar \nal objetivo.",
            "language": {
                "name": "es",
                "url": "/pokedex/language/7/"
            },
            "version_group": {
                "name": "omega-ruby-alpha-sapphire",
                "url": "/pokedex/version-group/16/"
            }
        },
        {
            "flavor_text": "Colpisce il bersaglio con tre sfere simultanee che\npossono paralizzarlo, scottarlo o congelarlo.",
            "language": {
                "name": "it",
                "url": "/pokedex/language/8/"
            },
            "version_group": {
                "name": "omega-ruby-alpha-sapphire",
                "url": "/pokedex/version-group/16/"
            }
        },
        {
            "flavor_text": "The user strikes with a simultaneous\nthree-beam attack. May also burn, freeze,\nor leave the target with paralysis.",
            "language": {
                "name": "en",
                "url": "/pokedex/language/9/"
            },
            "version_group": {
                "name": "omega-ruby-alpha-sapphire",
                "url": "/pokedex/version-group/16/"
            }
        },
        {
            "flavor_text": "\uff13\u3064\u306e\u3000\u5149\u7dda\u3067\u3000\u653b\u6483\u3059\u308b\u3002\n\u307e\u3072\u304b\u3000\u3084\u3051\u3069\u304b\u3000\u3053\u304a\u308a\u72b6\u614b\u306e\n\u3069\u308c\u304b\u306b\u3000\u3059\u308b\u3053\u3068\u304c\u3000\u3042\u308b\u3002",
            "language": {
                "name": "ja",
                "url": "/pokedex/language/11/"
            },
            "version_group": {
                "name": "omega-ruby-alpha-sapphire",
                "url": "/pokedex/version-group/16/"
            }
        },
        {
            "flavor_text": "\uff13\u3064\u306e\u3000\u3053\u3046\u305b\u3093\u3067\u3000\u3053\u3046\u3052\u304d\u3059\u308b\u3002\n\u307e\u3072\u304b\u3000\u3084\u3051\u3069\u304b\u3000\u3053\u304a\u308a\u3058\u3087\u3046\u305f\u3044\u306e\n\u3069\u308c\u304b\u306b\u3000\u3059\u308b\u3053\u3068\u304c\u3000\u3042\u308b\u3002",
            "language": {
                "name": "ja-Hrkt",
                "url": "/pokedex/language/1/"
            },
            "version_group": {
                "name": "sun-moon",
                "url": "/pokedex/version-group/17/"
            }
        },
        {
            "flavor_text": "3\uac1c\uc758 \uad11\uc120\uc73c\ub85c \uacf5\uaca9\ud55c\ub2e4.\n\ub9c8\ube44, \ud654\uc0c1 \ub610\ub294 \uc5bc\uc74c \uc0c1\ud0dc \uc911\n\uc5b4\ub290 \ud558\ub098\ub85c \ub9cc\ub4e4 \ub54c\uac00 \uc788\ub2e4.",
            "language": {
                "name": "ko",
                "url": "/pokedex/language/3/"
            },
            "version_group": {
                "name": "sun-moon",
                "url": "/pokedex/version-group/17/"
            }
        },
        {
            "flavor_text": "\u7528\uff13\u7a2e\u5149\u7dda\u9032\u884c\u653b\u64ca\u3002\n\u6709\u6642\u6703\u8b93\u5c0d\u624b\u9677\u5165\n\u9ebb\u75fa\u3001\u707c\u50b7\u6216\u51b0\u51cd\u7684\u72c0\u614b\u3002",
            "language": {
                "name": "zh-Hant",
                "url": "/pokedex/language/4/"
            },
            "version_group": {
                "name": "sun-moon",
                "url": "/pokedex/version-group/17/"
            }
        },
        {
            "flavor_text": "Le lanceur envoie trois boules d\u2019\u00e9nergie\nsimultan\u00e9ment. Peut aussi paralyser, br\u00fbler ou\ngeler l\u2019ennemi.",
            "language": {
                "name": "fr",
                "url": "/pokedex/language/5/"
            },
            "version_group": {
                "name": "sun-moon",
                "url": "/pokedex/version-group/17/"
            }
        },
        {
            "flavor_text": "Feuert drei Strahlen ab. Verursacht eventuell\nParalyse, Verbrennung oder Einfrieren.",
            "language": {
                "name": "de",
                "url": "/pokedex/language/6/"
            },
            "version_group": {
                "name": "sun-moon",
                "url": "/pokedex/version-group/17/"
            }
        },
        {
            "flavor_text": "Ataque triple que puede paralizar, quemar o congelar\nal objetivo.",
            "language": {
                "name": "es",
                "url": "/pokedex/language/7/"
            },
            "version_group": {
                "name": "sun-moon",
                "url": "/pokedex/version-group/17/"
            }
        },
        {
            "flavor_text": "Colpisce il bersaglio con tre sfere simultanee che\npossono paralizzarlo, scottarlo o congelarlo.",
            "language": {
                "name": "it",
                "url": "/pokedex/language/8/"
            },
            "version_group": {
                "name": "sun-moon",
                "url": "/pokedex/version-group/17/"
            }
        },
        {
            "flavor_text": "The user strikes with a simultaneous three-beam\nattack. May also burn, freeze, or paralyze the target.",
            "language": {
                "name": "en",
                "url": "/pokedex/language/9/"
            },
            "version_group": {
                "name": "sun-moon",
                "url": "/pokedex/version-group/17/"
            }
        },
        {
            "flavor_text": "\uff13\u3064\u306e\u3000\u5149\u7dda\u3067\u3000\u653b\u6483\u3059\u308b\u3002\n\u307e\u3072\u304b\u3000\u3084\u3051\u3069\u304b\u3000\u3053\u304a\u308a\u72b6\u614b\u306e\n\u3069\u308c\u304b\u306b\u3000\u3059\u308b\u3053\u3068\u304c\u3000\u3042\u308b\u3002",
            "language": {
                "name": "ja",
                "url": "/pokedex/language/11/"
            },
            "version_group": {
                "name": "sun-moon",
                "url": "/pokedex/version-group/17/"
            }
        },
        {
            "flavor_text": "\u7528\uff13\u79cd\u5149\u7ebf\u8fdb\u884c\u653b\u51fb\u3002\n\u6709\u65f6\u4f1a\u8ba9\u5bf9\u624b\u9677\u5165\n\u9ebb\u75f9\u3001\u707c\u4f24\u6216\u51b0\u51bb\u7684\u72b6\u6001\u3002",
            "language": {
                "name": "zh-Hans",
                "url": "/pokedex/language/12/"
            },
            "version_group": {
                "name": "sun-moon",
                "url": "/pokedex/version-group/17/"
            }
        },
        {
            "flavor_text": "\uff13\u3064\u306e\u3000\u3053\u3046\u305b\u3093\u3067\u3000\u3053\u3046\u3052\u304d\u3059\u308b\u3002\n\u307e\u3072\u304b\u3000\u3084\u3051\u3069\u304b\u3000\u3053\u304a\u308a\u3058\u3087\u3046\u305f\u3044\u306e\n\u3069\u308c\u304b\u306b\u3000\u3059\u308b\u3053\u3068\u304c\u3000\u3042\u308b\u3002",
            "language": {
                "name": "ja-Hrkt",
                "url": "/pokedex/language/1/"
            },
            "version_group": {
                "name": "ultra-sun-ultra-moon",
                "url": "/pokedex/version-group/18/"
            }
        },
        {
            "flavor_text": "3\uac1c\uc758 \uad11\uc120\uc73c\ub85c \uacf5\uaca9\ud55c\ub2e4.\n\ub9c8\ube44, \ud654\uc0c1 \ub610\ub294 \uc5bc\uc74c \uc0c1\ud0dc \uc911\n\uc5b4\ub290 \ud558\ub098\ub85c \ub9cc\ub4e4 \ub54c\uac00 \uc788\ub2e4.",
            "language": {
                "name": "ko",
                "url": "/pokedex/language/3/"
            },
            "version_group": {
                "name": "ultra-sun-ultra-moon",
                "url": "/pokedex/version-group/18/"
            }
        },
        {
            "flavor_text": "\u7528\uff13\u7a2e\u5149\u7dda\u9032\u884c\u653b\u64ca\u3002\n\u6709\u6642\u6703\u8b93\u5c0d\u624b\u9677\u5165\n\u9ebb\u75fa\u3001\u707c\u50b7\u6216\u51b0\u51cd\u7684\u72c0\u614b\u3002",
            "language": {
                "name": "zh-Hant",
                "url": "/pokedex/language/4/"
            },
            "version_group": {
                "name": "ultra-sun-ultra-moon",
                "url": "/pokedex/version-group/18/"
            }
        },
        {
            "flavor_text": "Le lanceur envoie trois boules d\u2019\u00e9nergie\nsimultan\u00e9ment. Peut aussi paralyser, br\u00fbler ou\ngeler l\u2019ennemi.",
            "language": {
                "name": "fr",
                "url": "/pokedex/language/5/"
            },
            "version_group": {
                "name": "ultra-sun-ultra-moon",
                "url": "/pokedex/version-group/18/"
            }
        },
        {
            "flavor_text": "Feuert drei Strahlen ab. Verursacht eventuell\nParalyse, Verbrennung oder Einfrieren.",
            "language": {
                "name": "de",
                "url": "/pokedex/language/6/"
            },
            "version_group": {
                "name": "ultra-sun-ultra-moon",
                "url": "/pokedex/version-group/18/"
            }
        },
        {
            "flavor_text": "Ataque triple que puede paralizar, quemar o congelar\nal objetivo.",
            "language": {
                "name": "es",
                "url": "/pokedex/language/7/"
            },
            "version_group": {
                "name": "ultra-sun-ultra-moon",
                "url": "/pokedex/version-group/18/"
            }
        },
        {
            "flavor_text": "Colpisce il bersaglio con tre sfere simultanee che\npossono paralizzarlo, scottarlo o congelarlo.",
            "language": {
                "name": "it",
                "url": "/pokedex/language/8/"
            },
            "version_group": {
                "name": "ultra-sun-ultra-moon",
                "url": "/pokedex/version-group/18/"
            }
        },
        {
            "flavor_text": "The user strikes with a simultaneous three-beam\nattack. May also burn, freeze, or paralyze the target.",
            "language": {
                "name": "en",
                "url": "/pokedex/language/9/"
            },
            "version_group": {
                "name": "ultra-sun-ultra-moon",
                "url": "/pokedex/version-group/18/"
            }
        },
        {
            "flavor_text": "\uff13\u3064\u306e\u3000\u5149\u7dda\u3067\u3000\u653b\u6483\u3059\u308b\u3002\n\u307e\u3072\u304b\u3000\u3084\u3051\u3069\u304b\u3000\u3053\u304a\u308a\u72b6\u614b\u306e\n\u3069\u308c\u304b\u306b\u3000\u3059\u308b\u3053\u3068\u304c\u3000\u3042\u308b\u3002",
            "language": {
                "name": "ja",
                "url": "/pokedex/language/11/"
            },
            "version_group": {
                "name": "ultra-sun-ultra-moon",
                "url": "/pokedex/version-group/18/"
            }
        },
        {
            "flavor_text": "\u7528\uff13\u79cd\u5149\u7ebf\u8fdb\u884c\u653b\u51fb\u3002\n\u6709\u65f6\u4f1a\u8ba9\u5bf9\u624b\u9677\u5165\n\u9ebb\u75f9\u3001\u707c\u4f24\u6216\u51b0\u51bb\u7684\u72b6\u6001\u3002",
            "language": {
                "name": "zh-Hans",
                "url": "/pokedex/language/12/"
            },
            "version_group": {
                "name": "ultra-sun-ultra-moon",
                "url": "/pokedex/version-group/18/"
            }
        },
        {
            "flavor_text": "\uff13\u3064\u306e\u3000\u3053\u3046\u305b\u3093\u3067\u3000\u3053\u3046\u3052\u304d\u3059\u308b\u3002\n\u307e\u3072\u304b\u3000\u3084\u3051\u3069\u304b\u3000\u3053\u304a\u308a\u3058\u3087\u3046\u305f\u3044\u306e\n\u3069\u308c\u304b\u306b\u3000\u3059\u308b\u3053\u3068\u304c\u3000\u3042\u308b\u3002",
            "language": {
                "name": "ja-Hrkt",
                "url": "/pokedex/language/1/"
            },
            "version_group": {
                "name": "lets-go-pikachu-lets-go-eevee",
                "url": "/pokedex/version-group/19/"
            }
        },
        {
            "flavor_text": "3\uac1c\uc758 \uad11\uc120\uc73c\ub85c \uacf5\uaca9\ud55c\ub2e4.\n\ub9c8\ube44, \ud654\uc0c1 \ub610\ub294 \uc5bc\uc74c \uc0c1\ud0dc \uc911\n\uc5b4\ub290 \ud558\ub098\ub85c \ub9cc\ub4e4 \ub54c\uac00 \uc788\ub2e4.",
            "language": {
                "name": "ko",
                "url": "/pokedex/language/3/"
            },
            "version_group": {
                "name": "lets-go-pikachu-lets-go-eevee",
                "url": "/pokedex/version-group/19/"
            }
        },
        {
            "flavor_text": "\u7528\uff13\u7a2e\u5149\u7dda\u9032\u884c\u653b\u64ca\u3002\n\u6709\u6642\u6703\u8b93\u5c0d\u624b\u9677\u5165\n\u9ebb\u75fa\u3001\u707c\u50b7\u6216\u51b0\u51cd\u7684\u72c0\u614b\u3002",
            "language": {
                "name": "zh-Hant",
                "url": "/pokedex/language/4/"
            },
            "version_group": {
                "name": "lets-go-pikachu-lets-go-eevee",
                "url": "/pokedex/version-group/19/"
            }
        },
        {
            "flavor_text": "Le lanceur envoie trois boules d\u2019\u00e9nergie simultan\u00e9ment.\nPeut aussi paralyser, br\u00fbler ou geler l\u2019ennemi.",
            "language": {
                "name": "fr",
                "url": "/pokedex/language/5/"
            },
            "version_group": {
                "name": "lets-go-pikachu-lets-go-eevee",
                "url": "/pokedex/version-group/19/"
            }
        },
        {
            "flavor_text": "Feuert drei Strahlen ab. Verursacht eventuell\nParalyse, Verbrennung oder Einfrieren.",
            "language": {
                "name": "de",
                "url": "/pokedex/language/6/"
            },
            "version_group": {
                "name": "lets-go-pikachu-lets-go-eevee",
                "url": "/pokedex/version-group/19/"
            }
        },
        {
            "flavor_text": "Ataque triple que puede paralizar, quemar o congelar\nal objetivo.",
            "language": {
                "name": "es",
                "url": "/pokedex/language/7/"
            },
            "version_group": {
                "name": "lets-go-pikachu-lets-go-eevee",
                "url": "/pokedex/version-group/19/"
            }
        },
        {
            "flavor_text": "Colpisce il bersaglio con tre sfere simultanee che\npossono paralizzarlo, scottarlo o congelarlo.",
            "language": {
                "name": "it",
                "url": "/pokedex/language/8/"
            },
            "version_group": {
                "name": "lets-go-pikachu-lets-go-eevee",
                "url": "/pokedex/version-group/19/"
            }
        },
        {
            "flavor_text": "The user strikes with a simultaneous three-beam attack.\nThis may also burn, freeze, or paralyze the target.",
            "language": {
                "name": "en",
                "url": "/pokedex/language/9/"
            },
            "version_group": {
                "name": "lets-go-pikachu-lets-go-eevee",
                "url": "/pokedex/version-group/19/"
            }
        },
        {
            "flavor_text": "\uff13\u3064\u306e\u3000\u5149\u7dda\u3067\u3000\u653b\u6483\u3059\u308b\u3002\n\u307e\u3072\u304b\u3000\u3084\u3051\u3069\u304b\u3000\u3053\u304a\u308a\u72b6\u614b\u306e\n\u3069\u308c\u304b\u306b\u3000\u3059\u308b\u3053\u3068\u304c\u3000\u3042\u308b\u3002",
            "language": {
                "name": "ja",
                "url": "/pokedex/language/11/"
            },
            "version_group": {
                "name": "lets-go-pikachu-lets-go-eevee",
                "url": "/pokedex/version-group/19/"
            }
        },
        {
            "flavor_text": "\u7528\uff13\u79cd\u5149\u7ebf\u8fdb\u884c\u653b\u51fb\u3002\n\u6709\u65f6\u4f1a\u8ba9\u5bf9\u624b\u9677\u5165\n\u9ebb\u75f9\u3001\u707c\u4f24\u6216\u51b0\u51bb\u7684\u72b6\u6001\u3002",
            "language": {
                "name": "zh-Hans",
                "url": "/pokedex/language/12/"
            },
            "version_group": {
                "name": "lets-go-pikachu-lets-go-eevee",
                "url": "/pokedex/version-group/19/"
            }
        },
        {
            "flavor_text": "\uff13\u3064\u306e\u3000\u3053\u3046\u305b\u3093\u3067\u3000\u3053\u3046\u3052\u304d\u3059\u308b\u3002\n\u307e\u3072\u304b\u3000\u3084\u3051\u3069\u304b\u3000\u3053\u304a\u308a\u3058\u3087\u3046\u305f\u3044\u306e\n\u3069\u308c\u304b\u306b\u3000\u3059\u308b\u3053\u3068\u304c\u3000\u3042\u308b\u3002",
            "language": {
                "name": "ja-Hrkt",
                "url": "/pokedex/language/1/"
            },
            "version_group": {
                "name": "sword-shield",
                "url": "/pokedex/version-group/20/"
            }
        },
        {
            "flavor_text": "3\uac1c\uc758 \uad11\uc120\uc73c\ub85c \uacf5\uaca9\ud55c\ub2e4.\n\ub9c8\ube44, \ud654\uc0c1 \ub610\ub294 \uc5bc\uc74c \uc0c1\ud0dc \uc911\n\uc5b4\ub290 \ud558\ub098\ub85c \ub9cc\ub4e4 \ub54c\uac00 \uc788\ub2e4.",
            "language": {
                "name": "ko",
                "url": "/pokedex/language/3/"
            },
            "version_group": {
                "name": "sword-shield",
                "url": "/pokedex/version-group/20/"
            }
        },
        {
            "flavor_text": "\u7528\uff13\u7a2e\u5149\u7dda\u9032\u884c\u653b\u64ca\u3002\n\u6709\u6642\u6703\u8b93\u5c0d\u624b\u9677\u5165\n\u9ebb\u75fa\u3001\u707c\u50b7\u6216\u51b0\u51cd\u7684\u72c0\u614b\u3002",
            "language": {
                "name": "zh-Hant",
                "url": "/pokedex/language/4/"
            },
            "version_group": {
                "name": "sword-shield",
                "url": "/pokedex/version-group/20/"
            }
        },
        {
            "flavor_text": "Le lanceur envoie trois boules d\u2019\u00e9nergie simultan\u00e9ment.\nPeut aussi paralyser, br\u00fbler ou geler l\u2019ennemi.",
            "language": {
                "name": "fr",
                "url": "/pokedex/language/5/"
            },
            "version_group": {
                "name": "sword-shield",
                "url": "/pokedex/version-group/20/"
            }
        },
        {
            "flavor_text": "Feuert drei Strahlen ab. Verursacht eventuell Paralyse,\nVerbrennung oder Einfrieren.",
            "language": {
                "name": "de",
                "url": "/pokedex/language/6/"
            },
            "version_group": {
                "name": "sword-shield",
                "url": "/pokedex/version-group/20/"
            }
        },
        {
            "flavor_text": "Ataque triple que puede paralizar, quemar o congelar\nal objetivo.",
            "language": {
                "name": "es",
                "url": "/pokedex/language/7/"
            },
            "version_group": {
                "name": "sword-shield",
                "url": "/pokedex/version-group/20/"
            }
        },
        {
            "flavor_text": "Colpisce il bersaglio con tre raggi di luce che\npossono paralizzarlo, scottarlo o congelarlo.",
            "language": {
                "name": "it",
                "url": "/pokedex/language/8/"
            },
            "version_group": {
                "name": "sword-shield",
                "url": "/pokedex/version-group/20/"
            }
        },
        {
            "flavor_text": "The user strikes with a simultaneous three-beam attack.\nThis may also burn, freeze, or paralyze the target.",
            "language": {
                "name": "en",
                "url": "/pokedex/language/9/"
            },
            "version_group": {
                "name": "sword-shield",
                "url": "/pokedex/version-group/20/"
            }
        },
        {
            "flavor_text": "\uff13\u3064\u306e\u3000\u5149\u7dda\u3067\u3000\u653b\u6483\u3059\u308b\u3002\n\u307e\u3072\u304b\u3000\u3084\u3051\u3069\u304b\u3000\u3053\u304a\u308a\u72b6\u614b\u306e\n\u3069\u308c\u304b\u306b\u3000\u3059\u308b\u3053\u3068\u304c\u3000\u3042\u308b\u3002",
            "language": {
                "name": "ja",
                "url": "/pokedex/language/11/"
            },
            "version_group": {
                "name": "sword-shield",
                "url": "/pokedex/version-group/20/"
            }
        },
        {
            "flavor_text": "\u7528\uff13\u79cd\u5149\u7ebf\u8fdb\u884c\u653b\u51fb\u3002\n\u6709\u65f6\u4f1a\u8ba9\u5bf9\u624b\u9677\u5165\n\u9ebb\u75f9\u3001\u707c\u4f24\u6216\u51b0\u51bb\u7684\u72b6\u6001\u3002",
            "language": {
                "name": "zh-Hans",
                "url": "/pokedex/language/12/"
            },
            "version_group": {
                "name": "sword-shield",
                "url": "/pokedex/version-group/20/"
            }
        }
    ],
    "generation": {
        "name": "generation-i",
        "url": "/pokedex/generation/1/"
    },
    "id": 161,
    "learned_by_pokemon": [
        {
            "name": "spearow",
            "url": "/pokedex/pokemon/21/"
        },
        {
            "name": "fearow",
            "url": "/pokedex/pokemon/22/"
        },
        {
            "name": "clefairy",
            "url": "/pokedex/pokemon/35/"
        },
        {
            "name": "clefable",
            "url": "/pokedex/pokemon/36/"
        },
        {
            "name": "jigglypuff",
            "url": "/pokedex/pokemon/39/"
        },
        {
            "name": "wigglytuff",
            "url": "/pokedex/pokemon/40/"
        },
        {
            "name": "dugtrio",
            "url": "/pokedex/pokemon/51/"
        },
        {
            "name": "abra",
            "url": "/pokedex/pokemon/63/"
        },
        {
            "name": "kadabra",
            "url": "/pokedex/pokemon/64/"
        },
        {
            "name": "alakazam",
            "url": "/pokedex/pokemon/65/"
        },
        {
            "name": "slowpoke",
            "url": "/pokedex/pokemon/79/"
        },
        {
            "name": "slowbro",
            "url": "/pokedex/pokemon/80/"
        },
        {
            "name": "magneton",
            "url": "/pokedex/pokemon/82/"
        },
        {
            "name": "doduo",
            "url": "/pokedex/pokemon/84/"
        },
        {
            "name": "dodrio",
            "url": "/pokedex/pokemon/85/"
        },
        {
            "name": "shellder",
            "url": "/pokedex/pokemon/90/"
        },
        {
            "name": "cloyster",
            "url": "/pokedex/pokemon/91/"
        },
        {
            "name": "drowzee",
            "url": "/pokedex/pokemon/96/"
        },
        {
            "name": "hypno",
            "url": "/pokedex/pokemon/97/"
        },
        {
            "name": "chansey",
            "url": "/pokedex/pokemon/113/"
        },
        {
            "name": "staryu",
            "url": "/pokedex/pokemon/120/"
        },
        {
            "name": "starmie",
            "url": "/pokedex/pokemon/121/"
        },
        {
            "name": "porygon",
            "url": "/pokedex/pokemon/137/"
        },
        {
            "name": "mewtwo",
            "url": "/pokedex/pokemon/150/"
        },
        {
            "name": "mew",
            "url": "/pokedex/pokemon/151/"
        },
        {
            "name": "togepi",
            "url": "/pokedex/pokemon/175/"
        },
        {
            "name": "togetic",
            "url": "/pokedex/pokemon/176/"
        },
        {
            "name": "slowking",
            "url": "/pokedex/pokemon/199/"
        },
        {
            "name": "porygon2",
            "url": "/pokedex/pokemon/233/"
        },
        {
            "name": "blissey",
            "url": "/pokedex/pokemon/242/"
        },
        {
            "name": "latias",
            "url": "/pokedex/pokemon/380/"
        },
        {
            "name": "latios",
            "url": "/pokedex/pokemon/381/"
        },
        {
            "name": "magnezone",
            "url": "/pokedex/pokemon/462/"
        },
        {
            "name": "togekiss",
            "url": "/pokedex/pokemon/468/"
        },
        {
            "name": "porygon-z",
            "url": "/pokedex/pokemon/474/"
        },
        {
            "name": "probopass",
            "url": "/pokedex/pokemon/476/"
        },
        {
            "name": "uxie",
            "url": "/pokedex/pokemon/480/"
        },
        {
            "name": "mesprit",
            "url": "/pokedex/pokemon/481/"
        },
        {
            "name": "azelf",
            "url": "/pokedex/pokemon/482/"
        },
        {
            "name": "beheeyem",
            "url": "/pokedex/pokemon/606/"
        },
        {
            "name": "hydreigon",
            "url": "/pokedex/pokemon/635/"
        },
        {
            "name": "genesect",
            "url": "/pokedex/pokemon/649/"
        },
        {
            "name": "type-null",
            "url": "/pokedex/pokemon/772/"
        },
        {
            "name": "silvally",
            "url": "/pokedex/pokemon/773/"
        },
        {
            "name": "magearna",
            "url": "/pokedex/pokemon/801/"
        },
        {
            "name": "alcremie",
            "url": "/pokedex/pokemon/869/"
        },
        {
            "name": "indeedee-male",
            "url": "/pokedex/pokemon/876/"
        },
        {
            "name": "dragapult",
            "url": "/pokedex/pokemon/887/"
        },
        {
            "name": "calyrex",
            "url": "/pokedex/pokemon/898/"
        },
        {
            "name": "sandy-shocks",
            "url": "/pokedex/pokemon/989/"
        },
        {
            "name": "iron-jugulis",
            "url": "/pokedex/pokemon/993/"
        },
        {
            "name": "alakazam-mega",
            "url": "/pokedex/pokemon/10037/"
        },
        {
            "name": "mewtwo-mega-x",
            "url": "/pokedex/pokemon/10043/"
        },
        {
            "name": "mewtwo-mega-y",
            "url": "/pokedex/pokemon/10044/"
        },
        {
            "name": "slowbro-mega",
            "url": "/pokedex/pokemon/10071/"
        },
        {
            "name": "dugtrio-alola",
            "url": "/pokedex/pokemon/10106/"
        },
        {
            "name": "magearna-original",
            "url": "/pokedex/pokemon/10147/"
        },
        {
            "name": "slowpoke-galar",
            "url": "/pokedex/pokemon/10164/"
        },
        {
            "name": "slowbro-galar",
            "url": "/pokedex/pokemon/10165/"
        },
        {
            "name": "slowking-galar",
            "url": "/pokedex/pokemon/10172/"
        },
        {
            "name": "calyrex-ice",
            "url": "/pokedex/pokemon/10193/"
        },
        {
            "name": "calyrex-shadow",
            "url": "/pokedex/pokemon/10194/"
        }
    ],
    "machines": [
        {
            "machine": {
                "url": "/pokedex/machine/560/"
            },
            "version_group": {
                "name": "lets-go-pikachu-lets-go-eevee",
                "url": "/pokedex/version-group/19/"
            }
        },
        {
            "machine": {
                "url": "/pokedex/machine/962/"
            },
            "version_group": {
                "name": "red-blue",
                "url": "/pokedex/version-group/1/"
            }
        },
        {
            "machine": {
                "url": "/pokedex/machine/963/"
            },
            "version_group": {
                "name": "yellow",
                "url": "/pokedex/version-group/2/"
            }
        },
        {
            "machine": {
                "url": "/pokedex/machine/1608/"
            },
            "version_group": {
                "name": "sword-shield",
                "url": "/pokedex/version-group/20/"
            }
        }
    ],
    "meta": {
        "ailment": {
            "name": "unknown",
            "url": "/pokedex/move-ailment/-1/"
        },
        "ailment_chance": 20,
        "category": {
            "name": "damage+ailment",
            "url": "/pokedex/move-category/4/"
        },
        "crit_rate": 0,
        "drain": 0,
        "flinch_chance": 0,
        "healing": 0,
        "max_hits": null,
        "max_turns": null,
        "min_hits": null,
        "min_turns": null,
        "stat_chance": 0
    },
    "name": "tri-attack",
    "names": [
        {
            "language": {
                "name": "ja-Hrkt",
                "url": "/pokedex/language/1/"
            },
            "name": "\u30c8\u30e9\u30a4\u30a2\u30bf\u30c3\u30af"
        },
        {
            "language": {
                "name": "ko",
                "url": "/pokedex/language/3/"
            },
            "name": "\ud2b8\ub77c\uc774\uc5b4\ud0dd"
        },
        {
            "language": {
                "name": "zh-Hant",
                "url": "/pokedex/language/4/"
            },
            "name": "\u4e09\u91cd\u653b\u64ca"
        },
        {
            "language": {
                "name": "fr",
                "url": "/pokedex/language/5/"
            },
            "name": "Triplattaque"
        },
        {
            "language": {
                "name": "de",
                "url": "/pokedex/language/6/"
            },
            "name": "Triplette"
        },
        {
            "language": {
                "name": "es",
                "url": "/pokedex/language/7/"
            },
            "name": "Triataque"
        },
        {
            "language": {
                "name": "it",
                "url": "/pokedex/language/8/"
            },
            "name": "Tripletta"
        },
        {
            "language": {
                "name": "en",
                "url": "/pokedex/language/9/"
            },
            "name": "Tri Attack"
        },
        {
            "language": {
                "name": "ja",
                "url": "/pokedex/language/11/"
            },
            "name": "\u30c8\u30e9\u30a4\u30a2\u30bf\u30c3\u30af"
        },
        {
            "language": {
                "name": "zh-Hans",
                "url": "/pokedex/language/12/"
            },
            "name": "\u4e09\u91cd\u653b\u51fb"
        }
    ],
    "past_values": [
        {
            "accuracy": null,
            "effect_chance": null,
            "effect_entries": [],
            "power": null,
            "pp": null,
            "type": null,
            "version_group": {
                "name": "gold-silver",
                "url": "/pokedex/version-group/3/"
            }
        }
    ],
    "power": 80,
    "pp": 10,
    "priority": 0,
    "stat_changes": [],
    "super_contest_effect": {
        "url": "/pokedex/super-contest-effect/5/"
    },
    "target": {
        "name": "selected-pokemon",
        "url": "/pokedex/move-target/10/"
    },
    "type": {
        "name": "normal",
        "url": "/pokedex/type/1/"
    }
}