{
    "id": 11,
    "name": "item",
    "names": [],
    "values": [
        {
            "name": "item-none",
            "url": "/pokedex/encounter-condition-value/43/"
        },
        {
            "name": "item-adamant-orb",
            "url": "/pokedex/encounter-condition-value/44/"
        },
        {
            "name": "item-lustrous-orb",
            "url": "/pokedex/encounter-condition-value/45/"
        },
        {
            "name": "item-helix-fossil",
            "url": "/pokedex/encounter-condition-value/46/"
        },
        {
            "name": "item-dome-fossil",
            "url": "/pokedex/encounter-condition-value/47/"
        },
        {
            "name": "item-old-amber",
            "url": "/pokedex/encounter-condition-value/48/"
        },
        {
            "name": "item-root-fossil",
            "url": "/pokedex/encounter-condition-value/49/"
        },
        {
            "name": "item-claw-fossil",
            "url": "/pokedex/encounter-condition-value/50/"
        },
        {
            "name": "item-odd-keystone",
            "url": "/pokedex/encounter-condition-value/68/"
        }
    ]
}